monitor_utils/__init__.py
monitor_utils/monitor_imap.py
monitor_utils/monitor_url_tag.py
monitor_utils/monitor_url_tag__implements.py
monitor_utils-0.0.4.dist-info/LICENSE
monitor_utils-0.0.4.dist-info/METADATA
monitor_utils-0.0.4.dist-info/WHEEL
monitor_utils-0.0.4.dist-info/top_level.txt
monitor_utils-0.0.4.dist-info/RECORD
