Metadata-Version: 2.1
Name: monitor-utils
Version: 0.0.4
Summary: monotir exact data (urlTag/Email) and alert on changes by email/telegram (threading)
Home-page: https://github.com/centroid457/
Author: Andrei Starichenko
Author-email: centroid@mail.ru
Project-URL: Source, https://github.com/centroid457/monitor_utils
Keywords: monitor changes,monitor data,url changes,url tag changes,url monitor,imap changes,email changes,imap monitor,email monitor,alerts,notifications,email alerts,telegram alerts
Classifier: Topic :: Software Development :: Libraries :: Python Modules
Classifier: Development Status :: 5 - Production/Stable
Classifier: License :: OSI Approved :: MIT License
Classifier: Programming Language :: Python
Classifier: Programming Language :: Python :: 3 :: Only
Classifier: Programming Language :: Python :: 3.11
Classifier: Operating System :: OS Independent
Classifier: Environment :: Console
Classifier: Intended Audience :: Developers
Classifier: Natural Language :: English
Classifier: Typing :: Typed
Requires-Python: >=3.6
License-File: LICENSE
